hyundai_kia_connect_api/ApiImpl.py
hyundai_kia_connect_api/ApiImplType1.py
hyundai_kia_connect_api/HyundaiBlueLinkApiBR.py
hyundai_kia_connect_api/HyundaiBlueLinkApiUSA.py
hyundai_kia_connect_api/KiaUvoApiAU.py
hyundai_kia_connect_api/KiaUvoApiCA.py
hyundai_kia_connect_api/KiaUvoApiCN.py
hyundai_kia_connect_api/KiaUvoApiEU.py
hyundai_kia_connect_api/KiaUvoApiIN.py
hyundai_kia_connect_api/KiaUvoApiUSA.py
hyundai_kia_connect_api/Token.py
hyundai_kia_connect_api/Vehicle.py
hyundai_kia_connect_api/VehicleManager.py
hyundai_kia_connect_api/__init__.py
hyundai_kia_connect_api/bluelink.py
hyundai_kia_connect_api/const.py
hyundai_kia_connect_api/exceptions.py
hyundai_kia_connect_api/utils.py
hyundai_kia_connect_api-4.4.0.dist-info/licenses/AUTHORS.rst
hyundai_kia_connect_api-4.4.0.dist-info/licenses/LICENSE
hyundai_kia_connect_api-4.4.0.dist-info/METADATA
hyundai_kia_connect_api-4.4.0.dist-info/WHEEL
hyundai_kia_connect_api-4.4.0.dist-info/entry_points.txt
hyundai_kia_connect_api-4.4.0.dist-info/top_level.txt
hyundai_kia_connect_api-4.4.0.dist-info/RECORD
