Metadata-Version: 2.4
Name: hyundai_kia_connect_api
Version: 4.4.0
Summary: Python Boilerplate contains all the boilerplate you need to create a Python package.
Home-page: https://github.com/Hyundai-Kia-Connect/hyundai_kia_connect_api
Author: Fuat Akgun
Author-email: fuatakgun@gmail.com
License: MIT license
Keywords: hyundai_kia_connect_api
Classifier: Development Status :: 2 - Pre-Alpha
Classifier: Intended Audience :: Developers
Classifier: License :: OSI Approved :: MIT License
Classifier: Natural Language :: English
Classifier: Programming Language :: Python :: 3.10
Requires-Python: >=3.10
License-File: LICENSE
License-File: AUTHORS.rst
Requires-Dist: beautifulsoup4>=4.10.0
Requires-Dist: requests
Requires-Dist: certifi>=2024.6.2
Requires-Dist: tzdata>=2025.2
Provides-Extra: google
Requires-Dist: geopy>=2.2.0; extra == "google"
Dynamic: author
Dynamic: author-email
Dynamic: classifier
Dynamic: description
Dynamic: home-page
Dynamic: keywords
Dynamic: license
Dynamic: license-file
Dynamic: provides-extra
Dynamic: requires-dist
Dynamic: requires-python
Dynamic: summary
